fastsort-0.1.1.dist-info/METADATA
fastsort-0.1.1.dist-info/WHEEL
fastsort/_core.pyi
fastsort/py.typed
fastsort/__init__.py
fastsort/_core.cpython-313t-s390x-linux-gnu.so
fastsort-0.1.1.dist-info/RECORD
